mem0/__init__.py
mem0/embeddings/__init__.py
mem0/embeddings/configs.py
mem0/embeddings/litellm.py
mem0/utils/__init__.py
mem0/utils/factory.py
mem0_embeddings_litellm_patch-1.0.8.dist-info/METADATA
mem0_embeddings_litellm_patch-1.0.8.dist-info/WHEEL
mem0_embeddings_litellm_patch-1.0.8.dist-info/top_level.txt
mem0_embeddings_litellm_patch-1.0.8.dist-info/RECORD
