Metadata-Version: 2.4
Name: mem0-embeddings-litellm-patch
Version: 1.0.8
Summary: Almost all known embedding model providers available via litellm patch
Author-email: Nocyphr <sgu@nocyphr.com>
Maintainer-email: Nocyphr <sgu@nocyphr.com>
License: MIT
Keywords: mem0,litellm,embeddings,ai,memory,patch
Requires-Python: >=3.8
Requires-Dist: mem0ai>=0.1.0
Requires-Dist: litellm>=1.0.0
